cnct/__init__.py
cnct/client/__init__.py
cnct/client/constants.py
cnct/client/exceptions.py
cnct/client/fluent.py
cnct/client/models/__init__.py
cnct/client/models/base.py
cnct/client/models/resourceset.py
cnct/client/utils.py
cnct/client/version.py
cnct/help/__init__.py
cnct/help/formatter.py
cnct/rql/__init__.py
cnct/rql/base.py
cnct/rql/utils.py
cnct/specs/__init__.py
cnct/specs/models.py
cnct/specs/parser.py
connect_api_client-21.0.0.dist-info/LICENSE
connect_api_client-21.0.0.dist-info/WHEEL
connect_api_client-21.0.0.dist-info/METADATA
connect_api_client-21.0.0.dist-info/RECORD
