Metadata-Version: 2.1
Name: connect-api-client
Version: 21.0.0
Summary: Connect Python OpenAPI Client
License: Apache-2.0
Author: CloudBlue
Requires-Python: >=3.6,<4.0
Classifier: License :: OSI Approved :: Apache Software License
Classifier: Programming Language :: Python :: 3
Classifier: Programming Language :: Python :: 3.6
Classifier: Programming Language :: Python :: 3.7
Classifier: Programming Language :: Python :: 3.8
Classifier: Programming Language :: Python :: 3.9
Requires-Dist: PyYAML (>=5.3.1,<6.0.0)
Requires-Dist: connect-markdown-renderer (>=1.0.0,<2.0.0)
Requires-Dist: requests (>=2.24.0,<3.0.0)
